LICENSE
MANIFEST.in
README.md
requirements.txt
setup.py
libact/__init__.py
libact.egg-info/PKG-INFO
libact.egg-info/SOURCES.txt
libact.egg-info/dependency_links.txt
libact.egg-info/requires.txt
libact.egg-info/top_level.txt
libact/base/__init__.py
libact/base/dataset.py
libact/base/interfaces.py
libact/labelers/__init__.py
libact/labelers/ideal_labeler.py
libact/labelers/interactive_labeler.py
libact/models/__init__.py
libact/models/logistic_regression.py
libact/models/perceptron.py
libact/models/sklearn_adapter.py
libact/models/svm.py
libact/models/multilabel/__init__.py
libact/models/multilabel/binary_relevance.py
libact/models/multilabel/dummy_clf.py
libact/query_strategies/__init__.py
libact/query_strategies/_hintsvm.c
libact/query_strategies/_hintsvm.pxd
libact/query_strategies/_hintsvm.pyx
libact/query_strategies/active_learning_by_learning.py
libact/query_strategies/density_weighted_meta.py
libact/query_strategies/density_weighted_uncertainty_sampling.py
libact/query_strategies/hintsvm.py
libact/query_strategies/query_by_committee.py
libact/query_strategies/quire.py
libact/query_strategies/random_sampling.py
libact/query_strategies/uncertainty_sampling.py
libact/query_strategies/variance_reduction.py
libact/query_strategies/multiclass/__init__.py
libact/query_strategies/multiclass/active_learning_with_cost_embedding.py
libact/query_strategies/multiclass/expected_error_reduction.py
libact/query_strategies/multiclass/hierarchical_sampling.py
libact/query_strategies/multiclass/mdsp.py
libact/query_strategies/multilabel/__init__.py
libact/query_strategies/multilabel/adaptive_active_learning.py
libact/query_strategies/multilabel/binary_minimization.py
libact/query_strategies/multilabel/cost_sensitive_reference_pair_encoding.py
libact/query_strategies/multilabel/maximum_margin_reduction.py
libact/query_strategies/multilabel/multilabel_with_auxiliary_learner.py
libact/query_strategies/src/hintsvm/COPYRIGHT
libact/query_strategies/src/hintsvm/libsvm_helper.c
libact/query_strategies/src/hintsvm/libsvm_helper.h
libact/query_strategies/src/hintsvm/svm.cpp
libact/query_strategies/src/hintsvm/svm.h
