Metadata-Version: 2.1
Name: libact
Version: 0.1.6
Summary: Pool-based active learning in Python
Home-page: https://github.com/ntucllab/libact
Author: Y.-Y. Yang, S.-C. Lee, Y.-A. Chung, T.-E. Wu, H.-T. Lin
Author-email: b01902066@csie.ntu.edu.tw, b01902010@csie.ntu.edu.tw, b01902040@csie.ntu.edu.tw, r00942129@ntu.edu.tw, htlin@csie.ntu.edu.tw
License: UNKNOWN
Platform: UNKNOWN
Classifier: Topic :: Scientific/Engineering
Classifier: Topic :: Scientific/Engineering :: Artificial Intelligence
Classifier: Programming Language :: Python :: 2.7
Classifier: Programming Language :: Python :: 3.4
Classifier: Programming Language :: Python :: 3.5
Classifier: Programming Language :: Python :: 3.6
